applitools/__init__.py
applitools/core_universal/__init__.py
applitools/core_universal/__main__.py
applitools/core_universal/instance.py
applitools/core_universal/server.py
applitools/core_universal/bin/core
core_universal-4.16.5.dist-info/LICENSE
core_universal-4.16.5.dist-info/METADATA
core_universal-4.16.5.dist-info/WHEEL
core_universal-4.16.5.dist-info/top_level.txt
core_universal-4.16.5.dist-info/RECORD
