Metadata-Version: 2.1
Name: core-universal
Version: 4.16.5
Summary: Applitools Eyes Core SDK Server
Home-page: http://www.applitools.com
Author: Applitools Team
Author-email: team@applitools.com
License: Applitools SDK License
Project-URL: Source, https://github.com/applitools/eyes.sdk.javascript1/tree/master/js/packages/core
Platform: Linux
Platform: MacOS
Platform: Windows
Classifier: Programming Language :: Python
Classifier: Development Status :: 4 - Beta
Classifier: Intended Audience :: Developers
Classifier: Operating System :: MacOS
Classifier: Operating System :: Microsoft :: Windows
Classifier: Operating System :: POSIX :: Linux
Classifier: Topic :: Software Development :: Quality Assurance
Classifier: Topic :: Software Development :: Testing
Requires-Python: <4,>=2.7
License-File: LICENSE
